Workbook
Name \\vv: #N/A
Name \0: #REF!
Name \0: #REF!
Name \0: #REF!
Name \1: #REF!
Name \1: #REF!
Name \1: #REF!
Name \a: #N/A
Name \b: #N/A
Name \c: #N/A
Name \d: #N/A
Name \ddd: #N/A
Name \e: #N/A
Name \f: #N/A
Name \g: #N/A
Name \h: #N/A
Name \i: #N/A
Name \j: #N/A
Name \K: #REF!
Name \K: #REF!
Name \K: #REF!
Name \l: #N/A
Name \m: #N/A
Name \n: #N/A
Name \o: #N/A
Name \p: #N/A
Name \pp: #N/A
Name \Q: #REF!
Name \Q: #REF!
Name \Q: #REF!
Name \qq: [2]Conver!#REF!
Name \qq: [2]Conver!#REF!
Name \qq: [2]Conver!#REF!
Name \r: #N/A
Name \s: #N/A
Name \t: #N/A
Name \u: #N/A
Name \v: #N/A
Name \vv: #N/A
Name \w: #N/A
Name \we: #N/A
Name \ww: #N/A
Name \wwe: #N/A
Name \x: '[3]XE-CPL'!#REF!
Name \x: '[3]XE-CPL'!#REF!
Name \x: '[3]XE-CPL'!#REF!
Name \x1: '[3]XE-CPL'!#REF!
Name \x1: '[3]XE-CPL'!#REF!
Name \x1: '[3]XE-CPL'!#REF!
Name \z: #N/A
Name \zz: #N/A
Name ______DAT1: [4]RA!#REF!
Name ______DAT1: [4]RA!#REF!
Name ______DAT1: [4]RA!#REF!
Name ______DAT2: [4]RA!#REF!
Name ______DAT2: [4]RA!#REF!
Name ______DAT2: [4]RA!#REF!
Name ______DAT3: [4]RA!#REF!
Name ______DAT3: [4]RA!#REF!
Name ______DAT6: [4]RA!#REF!

Sheet CAPEX SUMMARY
A1: AGRIAUTO STAMPING COMPANY PVT LIMITED
A2: REPAIR & MAINTENANCE BUDGET
A3: 2026-27
A5: Sr. # | B5: DESCRIPTION OF ITEM | C5: QTY. | D5: NEW USED/REFUR | E5: IMPORT / LOCAL | F5: FY 2026-27 (Rs.) | WZI5: Budget Utilization | WZJ5: Remaining budget | WZK5: Utilization %
A7: A | B7: CARRY FORWARD PROJECTS / PROJECTS | E7: Local | F7: ='CAPEX Detail'!H13 -> 27958050
A9: B | B9: PROPOSED CAPEX | E9: Import | F9: ='CAPEX Detail'!H49 -> 3.1072048e+08
A11: C | B11: Vehicles | E11: Import | F11: ='CAPEX Detail'!H62 -> 41430500
B14: Grand Total | D14: Total (A+B) | F14: =F7+F9+F11 -> 3.8010903e+08

Sheet CAPEX Detail
A1: AGRIAUTO STAMPING COMPANY
A2: CAPITAL EXPENDITURE
A3: BUDGET - 2026-27
A5: Sr.# | B5: DESCRIPTION OF ITEM | C5: CLASSIFICATION | D5: QTY. | E5: SOURCE/ ORIGIN | F5: DATE | G5: Category | H5: Rs. | I5: JUSTIFICATIONS
H6: AMOUNT
L7: 2000005372
A8: A | B8: CARRY FORWARD PROJECTS / PROJECTS
A9: A-1 | B9: DEVELOPMENT PROJECTS
A10: A- | B10: CF Deck Extension work | C10: New | D10: Var | E10: Local | F10: Sep'26 | H10: 17958050 | I10: Work under progress.
B11: 02 Welding Guns For YXO Project | C11: New | F11: Nov'26 | H11: 10000000 | L11: =1185121.2*1.8 -> 2133218.2
E13: TOTAL- >>>>>> A | H13: =SUM(H10:H12) -> 27958050
A15: B | B15: PROPOSED CAPEX
A16: B-1 | B16: Upgradation Works/Projects
A17: A- | B17: 200KW Solar energy generation system with BESS | C17: New | D17: 1 | E17: Import/Local | F17: 46419 | H17: 20000000 | I17: Panels will be installed on Warehouse building at ASC after extension along with batteries | J17: Quotation check with weight and clearance
A18: B- | B18: New Blanking Pess ( 500T - Used condition) | C18: Refurbish | D18: 1 | E18: Import/Local | F18: 46413 | H18: 100000000 | I18: Quotation awaited from Horiuchi san. Estimated price added | J18: Quotation check with weight and clearance
A19: C- | B19: CNC vertical Machining Center (1500x800)mm | C19: New | D19: 1 | E19: Import/Local | F19: Dec'26 | H19: =(146600*295*1.1)+5000000+2000000 -> 54571700 | I19: 146,600*280 + 10% Clearance & Duty + 1M Machine inspection + 1M Installation + 5M Foundation
A20: D- | B20: Shearing Machine | C20: New | D20: 1 | E20: Import/Local | F20: Nov'26 | H20: =50000*295*1.2 -> 17700000 | I20: 50000*280 + 5% Clearance & Duty + Installation Cost
B21: Welding Robot (Automation) | C21: New | D21: 1 | E21: Import/Local | F21: Dec'26 | H21: 20000000 | I21: Productivity Improvement for Yaris Line
A22: E- | B22: Auto Die Cart | C22: New | D22: 1 | E22: Import/Local | F22: Dec'26 | H22: 5000000 | I22: For New die area, replaced from manual to auto
A23: F- | B23: Racks for Extended C.C Warehouse Building - 36 No. Racks | H23: 0 | I23: RM
E24: TOTAL- >>>>>> B-1 | H24: =SUM(H17:H23) -> 217271700
A26: B-2 | B26: Misc Department
A27: A- | B27: Portable Inverter Tig+Stick welding Machine (DM&Fab) | C27: New | D27: 2 | E27: Local | F27: Dec'26 | H27: =546000+975000 -> 1521000
A28: B- | B28: AC For GL & Asakai Room | C28: Replacement | D28: 2 | E28: Local | F28: Sep'26 | H28: 1000000
A29: C- | B29: Suzuki Carry | C29: New | D29: 1 | E29: Local | F29: Dec'26
A30: D- | B30: Truck & Deck for Supplies of new upcoming projects (YXO, W&D) | C30: New | D30: 1 | E30: Local | F30: Oct'26 | H30: 11200000 | I30: 9.9M for Truck + 1.1M for Deck
A31: E- | B31: Fork Lifter 2/3.5 Ton Capacity (EV) | C31: Refurbish | D31: 1 | E31: Local | F31: Nov'26 | H31: =5000000*1.1 -> 5500000 | I31: Estimated. Quotation awaited from Horiuchi san
A32: F- | B32: Battery Stacker 2 Ton Capacity | C32: Replacement | D32: 2 | E32: Local | F32: Dec'26 | H32: 16905900 | I32: (23500x327)*10& Duty & Clearance
A33: G | B33: Air Dryer For C.C Compressor | C33: New | D33: 1 | E33: Local | F33: Dec'26 | H33: 1746000 | I33: (4643*327)+15% Freight Duty& Clearance
A34: I- | B34: QLED for Asakai Room/QC/SCM (Digitization) | C34: New | D34: 3 | E34: Local | F34: Sep'26 | H34: =240000+340000+370000 -> 950000
E36: TOTAL- >>>>>> B-3 | H36: =SUM(H27:H34) -> 38822900
A38: B-3 | B38: IT - Server & Accessories
A39: A- | B39: Computer Sets | C39: Replacement | D39: 10 | E39: Local | H39: 6705800
A40: B- | B40: Desktop PC / Laptops | D40: 6 | E40: Local | H40: 4000000
A41: C- | B41: Laptops | D41: 6 | E41: Local | H41: 2700000
A42: D- | B42: Projector | D42: 1 | E42: Local | H42: 305084.74
A43: E- | B43: Network Switch | D43: 2 | E43: Local | H43: 790000
A44: F- | B44: HP Laser Printer | C44: Replacement | D44: 1 | E44: Local | H44: 125000
A45: G- | B45: Implementatin Cost with SAP Migration Project (5year) | D45: 1 | E45: Local | F45: Feb'27 | H45: 40000000
E47: TOTAL- >>>>>> B-4 | H47: =SUM(H39:H45) -> 54625885
E49: TOTAL- >>>>>> B | H49: =H36+H47+H24 -> 3.1072048e+08
B51: GRAND TOTAL A+B >>>>>>> | E51: B+A | H51: =H13+H49 -> 3.3867853e+08
A53: C | B53: As per policy
A54: 1 | B54: Car (Replacement on maturity) | C54: Replacement | D54: 1 | E54: Local | H54: =20527000+4809000+4809000+6411500 -> 36556500
A55: =A54+1 -> 2 | B55: Car (Promotion Cases) | C55: New | D55: 1 | E55: Local | H55: 4649000
A56: =A55+1 -> 3 | B56: Mobile Phones (Senior Managers and Above) | C56: Replacement | E56: Local
A57: =A56+1 -> 4 | B57: Mobile Phones (Managers) | C57: New | D57: 1 | E57: Local | H57: 225000
E62: TOTAL- >>>>>> C | H62: =SUM(H54:H57) -> 41430500
B65: GRAND TOTAL A + B + C >>>>>>> | H65: =H51+H62 -> 3.8010903e+08
I66: Residual value | J66: Depreciation
G67: CAPEX - Vehicles | H67: =H54+H55 -> 41205500 | I67: =H67*35% -> 14421925 | J67: =(H67-I67)/5 -> 5356715 | K67: COS | L67: =J67+J68 -> 32258033 | M67: =L67/1000 -> 32258.033
G68: CAPEX - other than Vehicles | H68: =H65-H69-H67 -> 2.9890353e+08 | I68: =H68*10% -> 29890353 | J68: =(H68-I68)/10 -> 26901318 | K68: COS
G69: CAPEX - Intangible Asset | H69: =H45 -> 40000000 | I69: 0 | J69: =(H69-I69)/5*5/12 -> 3333333.3 | K69: Admin | M69: =J69/1000 -> 3333.3333
J70: =SUM(J67:J69) -> 35591366

Sheet RM-SUMMARY
A1: AGRIAUTO STAMPING COMPANY PVT LIMITED
A2: REPAIR & MAINTENANCE BUDGET - STAMPING & CATALYTIC CONVERTOR
A3: 2026-27
A5: Sr. # | B5: DESCRIPTION OF ITEM | C5: QTY. | D5: NEW USED/REFUR | E5: IMPORT / LOCAL | F5: FY 2025-26 (Rs.) | G5: Act Est. 2025-26 (Rs.) | H5: FY 2026-27 (Rs.) | I5: Differ | WZI5: Budget Utilization | WZJ5: Remaining budget | WZK5: Utilization %
A7: A | B7: Annual Service contracts | E7: Local | F7: ='RM Detail'!F19 -> 7725000 | G7: ='RM Detail'!G19 -> 5052208 | H7: ='RM Detail'!H19 -> 7850000 | I7: =H7-G7 -> 2797792
A9: B | B9: Critical Machine Spares, Tools | E9: Import | F9: ='RM Detail'!F33 -> 20141720 | G9: ='RM Detail'!G33 -> 26719621 | H9: ='RM Detail'!H33 -> 26277194 | I9: =H9-G9 -> -442426.54
I10: =H10-G10 -> 0
A11: C | B11: Improvement & Repair works | E11: Import | F11: ='RM Detail'!F62 -> 16099295 | G11: ='RM Detail'!G62 -> 12029634 | H11: ='RM Detail'!H62 -> 16660500 | I11: =H11-G11 -> 4630866
I12: =H12-G12 -> 0
A13: D | B13: Truck & Forklifter Maintenance | E13: Local | F13: ='RM Detail'!F77 -> 2420000 | G13: ='RM Detail'!G77 -> 4111146.6 | H13: ='RM Detail'!H77 -> 7675329.7 | I13: =H13-G13 -> 3564183
I14: =H14-G14 -> 0
A15: E | B15: General Maintenance & Items | E15: Local | F15: ='RM Detail'!F96 -> 11745732 | G15: ='RM Detail'!G96 -> 16325234 | H15: ='RM Detail'!H96 -> 15668402 | I15: =H15-G15 -> -656831.85
I16: =H16-G16 -> 0
A17: F | B17: Quality | E17: Local | F17: ='RM Detail'!F111 -> 4329300 | G17: ='RM Detail'!G111 -> 2333954 | H17: ='RM Detail'!H111 -> 2487000 | I17: =H17-G17 -> 153046
I18: =H18-G18 -> 0
A19: G | B19: Hand Tools | E19: Local | F19: ='RM Detail'!F119 -> 2355615 | G19: ='RM Detail'!G119 -> 1910042.5 | H19: ='RM Detail'!H119 -> 3468365 | I19: =H19-G19 -> 1558322.5
I20: =H20-G20 -> 0
A21: H | B21: Admin | E21: Local | F21: ='RM Detail'!F131 -> 1600000 | G21: ='RM Detail'!G131 -> 3092968.2 | H21: ='RM Detail'!H131 -> 4300000 | I21: =H21-G21 -> 1207031.8
I22: =H22-G22 -> 0
A23: I | B23: IT | E23: Local | F23: ='RM Detail'!F161 -> 8803912 | G23: ='RM Detail'!G161 -> 6853605 | H23: ='RM Detail'!H161 -> 28324568 | I23: =H23-G23 -> 21470963
I24: =H24-G24 -> 0
A25: J | B25: Oil / Lubricants | E25: Local | F25: ='RM Detail'!F166 -> 4966140 | G25: ='RM Detail'!G166 -> 4828162 | H25: ='RM Detail'!H166 -> 0 | I25: =H25-G25 -> -4828162
I26: =H26-G26 -> 0
A27: K | B27: Material Handling | E27: Local | F27: ='RM Detail'!F172 -> 10397008 | G27: ='RM Detail'!G172 -> 14411500 | H27: ='RM Detail'!H172 -> 15000000 | I27: =H27-G27 -> 588500
I28: =H28-G28 -> 0
A29: L | B29: Sap Rise | E29: Local | H29: ='RM Detail'!H177 -> 58000000 | I29: =H29-G29 -> 58000000
I30: =H30-G30 -> 0
I31: =H31-G31 -> 0
D32: GRAND TOTAL | F32: =SUM(F7:F31) -> 90583722 | G32: =SUM(G7:G31) -> 97668075 | H32: =SUM(H7:H31) -> 1.8571136e+08 | I32: =H32-G32 -> 88043284

Sheet RM Detail
A1: AGRIAUTO STAMPING COMPANY PVT LIMITED
A2: REPAIR & MAINTENANCE BUDGET
A3: 2026-27
I4: Approved
A5: Sr. # | B5: DESCRIPTION OF ITEM | C5: QTY. | D5: NEW USED/REFUR | E5: IMPORT / LOCAL | F5: Budgeted Amount (Rs.) | G5: Budget Utilization | H5: Proposed Budget 26-27 | I5: Budget Utilization | J5: Remaining budget | L5: 2000005372 | M5: 2000005358 | N5: 2000005356 | O5: 2000005403 | P5: 2000005494 | Q5: 2000005476
A7: A | B7: Annual Service contracts
A8: 1- | B8: Weigh Bridge Calibration & Service Contract | C8: 1 | D8: New | E8: Local | F8: 50000 | G8: 48825 | H8: 50000 | I8: =SUM(L8:XEZ8) -> 0 | J8: =H8-I8 -> 50000
A9: 2- | B9: Overhead Crane 20 T + 20/10T, GH Crane and Street Crane | C9: 4 | D9: New | E9: Local | F9: =1350000 -> 1350000 | G9: 1306024 | H9: =1350000 -> 1350000 | I9: =SUM(L9:XEZ9) -> 0 | J9: =H9-I9 -> 1350000
A10: 3- | B10: Vibration Analysis (4 Times/Year) | C10: 6 | D10: New | E10: Local | F10: 250000 | G10: 0 | H10: 250000 | I10: =SUM(L10:XEZ10) -> 0 | J10: =H10-I10 -> 250000
A11: 4- | B11: Compressor efficiency analysis by AVS (6 Times/ Yr) | C11: 6 | D11: New | E11: Local | F11: 150000 | G11: 307530 | H11: 450000 | I11: =SUM(L11:XEZ11) -> 0 | J11: =H11-I11 -> 450000
A12: 5- | B12: Generator 135KVA | C12: 1 | D12: New | E12: Local | F12: 100000 | G12: 0 | H12: 100000 | I12: =SUM(L12:XEZ12) -> 0 | J12: =H12-I12 -> 100000
A13: 6- | B13: Horiuchi Contract for Press machines | C13: 5 | D13: New | E13: Local/Import | F13: 3000000 | G13: 546170 | H13: 3000000 | I13: =SUM(L13:XEZ13) -> 0 | J13: =H13-I13 -> 3000000
A14: 7- | B14: Solar Maintenance Annual Contract REON | C14: 1 | D14: New | E14: Local | F14: 2200000 | G14: 2282276 | H14: 2000000 | I14: =SUM(L14:XEZ14) -> 0 | J14: =H14-I14 -> 2000000
A15: 8- | B15: Annual Service Contract for CCTV Camera System | C15: 1 | D15: New | E15: Local | F15: 175000 | G15: 180000 | H15: 200000 | I15: =SUM(L15:XEZ15) -> 0 | J15: =H15-I15 -> 200000
A16: 9- | B16: Annual Service Contract for Canteen Lift | C16: 1 | D16: New | E16: Local | F16: 250000 | G16: 196600 | H16: 250000 | I16: =SUM(L16:XEZ16) -> 0 | J16: =H16-I16 -> 250000
A17: 10- | B17: Annual Service Contract for Attendance Machine | C17: 1 | D17: New | E17: Local | F17: 200000 | G17: 184783 | H17: 200000 | I17: =SUM(L17:XEZ17) -> 0 | J17: =H17-I17 -> 200000
A19: Sub Total (A): | F19: =SUM(F8:F17) -> 7725000 | G19: =SUM(G8:G17) -> 5052208 | H19: =SUM(H8:H17) -> 7850000 | I19: =SUM(I8:I17) -> 0 | J19: =SUM(J8:J17) -> 7850000
A20: B | B20: Critical Machine Spares Backup:
A21: 1- | B21: Stamping Shop | C21: 9 | D21: New/Refurbished | E21: Import/Local | F21: 4000000 | G21: 5250525.3 | H21: 3500000 | I21: =SUM(L21:XEZ21) -> 0 | J21: =H21-I21 -> 3500000
A22: 2- | B22: Over Head Cranes 20T & 20/10T | C22: 4 | D22: New/Refurbished | E22: Import/Local | F22: 4000000 | G22: 5100500.3 | H22: 2000000 | I22: =SUM(L22:XEZ22) -> 0 | J22: =H22-I22 -> 2000000
A23: 3- | B23: Weld Shop (Maintenance Spares) | C23: var | D23: New/Refurbished | E23: Import/Local | F23: 3500000 | G23: 4079725.7 | H23: 4000000 | I23: =SUM(L23:XEZ23) -> 0 | J23: =H23-I23 -> 4000000
A24: 4- | B24: Weld Shop (Production Spares) | C24: Var | D24: New/Refurbished | E24: Import/Local | F24: 491720 | G24: 516470 | H24: 790194 | I24: =SUM(L24:XEZ24) -> 0 | J24: =H24-I24 -> 790194
A25: 5- | B25: Die Center Machines | C25: 7 | D25: New/Refurbished | E25: Import/Local | F25: 1000000 | G25: 800000 | H25: 1000000 | I25: =SUM(L25:XEZ25) -> 0 | J25: =H25-I25 -> 1000000
A26: 6- | B26: Cooling Tower Spares | C26: 2 | D26: New | E26: Local | F26: 750000 | G26: 535747 | H26: 950000 | I26: =SUM(L26:XEZ26) -> 0 | J26: =H26-I26 -> 950000
A27: 7- | B27: Repairing of Chillers | C27: 3 | D27: New | E27: Local | F27: 650000 | G27: 530000 | H27: 287000 | I27: =SUM(L27:XEZ27) -> 0 | J27: =H27-I27 -> 287000
A28: 8- | B28: Catalytic Convertor Plant Machine spares | C28: 11 | D28: New | E28: Import/Local | F28: 1000000 | G28: 2150000 | H28: 3500000 | I28: =SUM(L28:XEZ28) -> 0 | J28: =H28-I28 -> 3500000
A29: 9- | B29: Compressor & Dryers Service Kits & Spare Parts | C29: 6 | D29: New | E29: Import/Local | F29: 4500000 | G29: 5285091.3 | H29: 6500000 | I29: =SUM(L29:XEZ29) -> 0 | J29: =H29-I29 -> 6500000
A30: 10- | B30: Canteen Lift Critical Spares | C30: 1 | D30: New | E30: Local | F30: 250000 | G30: 210000 | H30: 250000 | I30: =SUM(L30:XEZ30) -> 0 | J30: =H30-I30 -> 250000
A31: 11- | B31: All Plant Machine Inverters (VFDs) | G31: 2261561 | H31: 3500000 | J31: =H31-I31 -> 3500000
A33: Sub Total (B): | F33: =SUM(F21:F30) -> 20141720 | G33: =SUM(G21:G31) -> 26719621 | H33: =SUM(H21:H32) -> 26277194 | I33: =SUM(I21:I32) -> 0 | J33: =SUM(J21:J32) -> 26277194
A35: C | B35: Improvement & Repair works
B36: Compressor Overhauling | C36: 2 | D36: New | E36: Local | F36: NR
A37: 1- | B37: Coloring work (Utility building & Plant) | C37: var | D37: New | E37: Local | F37: =1000000 -> 1000000 | G37: 637820 | H37: 500000 | I37: =SUM(L37:XEZ37) -> 0 | J37: =H37-I37 -> 500000
A38: 2- | B38: Coloring Work of All Komatsu Press Machine | C38: 4 | D38: New | E38: Local | F38: 550000 | G38: 550000 | H38: 0 | I38: =SUM(L38:XEZ38) -> 0 | J38: =H38-I38 -> 0
A39: 3- | B39: Repair, repaint of bins, racks and trolleys etc | C39: var | D39: New | E39: Local | F39: 500000 | G39: 135891 | H39: 500000 | I39: =SUM(L39:XEZ39) -> 0 | J39: =H39-I39 -> 500000
A40: 4- | B40: Wheel & Color for Scrap Bins (Press Shop) | C40: Var | D40: New | E40: Local | F40: 118800 | G40: 0 | H40: 170500 | I40: =SUM(L40:XEZ40) -> 0 | J40: =H40-I40 -> 170500
A41: 5- | B41: Halogen Bulb Replacement with LED Lights DDC& Press Area | C41: Var | D41: New | E41: Local | F41: 1020000 | G41: 1013564.1 | H41: 500000 | I41: =SUM(L41:XEZ41) -> 0 | J41: =H41-I41 -> 500000
A42: 6- | B42: LED's Replacement Whole Plant | C42: Var | D42: New | E42: Local | F42: 3000000 | G42: 2699682 | H42: 0 | I42: =SUM(L42:XEZ42) -> 0 | J42: =H42-I42 -> 0
A43: 7- | B43: Fire Alarm Maintenance | C43: 1 | D43: New | E43: Local | F43: 350000 | G43: 199600 | H43: 350000 | I43: =SUM(L43:XEZ43) -> 0 | J43: =H43-I43 -> 350000
A44: 8- | B44: All Plant AC/Refrigeration Repair & Maintenance | C44: Var | D44: New | E44: Local | F44: 750000 | G44: 278000 | H44: 750000 | I44: =SUM(L44:XEZ44) -> 0 | J44: =H44-I44 -> 750000
A45: 7- | B45: CO2 Air Ducting | C45: 1 | D45: New | E45: Local | G45: 1600 | I45: =SUM(L45:XEZ45) -> 0 | J45: =H45-I45 -> 0
A46: 9- | B46: QC Office and GL Room Repairing | C46: 1 | D46: New | E46: Local | F46: - | G46: 0 | I46: =SUM(L46:XEZ46) -> 0 | J46: =H46-I46 -> 0
A47: 10- | B47: Solar Power Factor Smart System | C47: 1 | D47: New | E47: Local | F47: 1000000 | G47: 643460 | H47: 0 | I47: =SUM(L47:XEZ47) -> 0 | J47: =H47-I47 -> 0
A48: 11- | B48: Die Repair | C48: 1 | D48: New | E48: Local | F48: 5846100 | G48: 2855455 | H48: 3500000 | I48: =SUM(L48:XEZ48) -> 95392.5 | J48: =H48-I48 -> 3404607.5 | M48: 95392.5
A49: 12- | B49: TIC for Inserts | C49: 1 | D49: New | E49: Local/Import | G49: 0 | I49: =SUM(L49:XEZ49) -> 0 | J49: =H49-I49 -> 0
A50: 13- | B50: Catalytic Convertor Tooling Repair & Development | C50: 1 | D50: New | E50: Local | F50: 964395 | G50: 335575 | H50: =440000+500000 -> 940000 | I50: =SUM(L50:XEZ50) -> 0 | J50: =H50-I50 -> 940000
A51: 14- | B51: Smart Monitoring of Press Production (AI project) | C51: 1 | D51: New | E51: Local | F51: 1000000 | G51: 0 | H51: 0 | I51: =SUM(L51:XEZ51) -> 0 | J51: =H51-I51 -> 0
A52: 15- | B52: Installation of Centralized Monitoring System | I52: =SUM(L52:XEZ52) -> 0 | J52: =H52-I52 -> 0
A53: 16- | B53: Exhaust system at MV, LV Room for Ventilation | H53: 950000 | I53: =SUM(L53:XEZ53) -> 0 | J53: =H53-I53 -> 950000
A54: 17- | B54: Plant Floor Repairing (Civil Work) | H54: 500000 | I54: =SUM(L54:XEZ54) -> 0 | J54: =H54-I54 -> 500000
A55: 18- | B55: plastic curtains for welding gantry (Weld shop) | H55: 1000000 | I55: =SUM(L55:XEZ55) -> 0 | J55: =H55-I55 -> 1000000
A56: 19- | B56: Small AI & IOT Projects | H56: 2500000 | I56: =SUM(L56:XEZ56) -> 0 | J56: =H56-I56 -> 2500000
A57: 20- | B57: Racks for Extended C.C Warehouse Building - 36 No. Racks | I57: =SUM(L57:XEZ57) -> 0 | J57: =H57-I57 -> 0
A58: 21- | B58: Purchase and installation of dehumidifiers in Weld and Press | H58: 1500000 | I58: =SUM(L58:XEZ58) -> 0 | J58: =H58-I58 -> 1500000
A59: 22- | B59: Installation of Centralized Monitoring System | G59: 2678986.9 | H59: 1000000 | I59: =SUM(L59:XEZ59) -> 0 | J59: =H59-I59 -> 1000000
A60: 23- | B60: Raw material inventory control by QR Code System | H60: 2000000 | I60: =SUM(L60:XEZ60) -> 0 | J60: =H60-I60 -> 2000000
A62: Sub Total (C): | F62: =SUM(F37:F51) -> 16099295 | G62: =SUM(G37:G60) -> 12029634 | H62: =SUM(H37:H60) -> 16660500 | I62: =SUM(I37:I60) -> 95392.5 | J62: =SUM(J37:J60) -> 16565108
A64: D | B64: Truck & Forklifter Maintenance
A65: 1- | B65: Repair Maintenance of Battery Stackers | C65: 4 | D65: New | E65: Local | F65: 300000 | G65: 625500 | H65: =1700000*1.1 -> 1870000 | I65: =SUM(L65:XEZ65) -> 0 | J65: =H65-I65 -> 1870000
A66: 2- | B66: Service & Maintenance of trucks | C66: 5 | D66: New | E66: Local | F66: 250000 | G66: 509005 | H66: 1090000 | I66: =SUM(L66:XEZ66) -> 0 | J66: =H66-I66 -> 1090000
A67: 3- | B67: Inspection, Service & Maintenance of Lifters 2T, 3.5T & 4T | C67: 3 | D67: New | E67: Local | F67: 500000 | G67: 837587 | H67: 1210000 | I67: =SUM(L67:XEZ67) -> 0 | J67: =H67-I67 -> 1210000
A68: 4- | B68: Spare Wheel & tires for Fork Lift 4T | C68: 2 | D68: New | E68: Local | F68: 130000 | G68: 921250.76 | H68: 0 | I68: =SUM(L68:XEZ68) -> 0 | J68: =H68-I68 -> 0
A69: 5- | B69: Spare Wheel & tires for Fork Lift 3.5T | C69: 2 | D69: New | E69: Local | F69: 120000 | G69: 120000.48 | H69: 242000 | I69: =SUM(L69:XEZ69) -> 0 | J69: =H69-I69 -> 242000
A70: 6- | B70: Spare Wheel & tires for Fork Lift 2T | C70: 2 | D70: New | E70: Local | F70: 150000 | G70: 150000.38 | H70: 676779.67 | I70: =SUM(L70:XEZ70) -> 0 | J70: =H70-I70 -> 676779.67
A71: 7- | B71: Tire Replacement for two trucks | C71: 3 | D71: New | E71: Local | F71: 120000 | G71: 122670 | H71: 420000 | I71: =SUM(L71:XEZ71) -> 0 | J71: =H71-I71 -> 420000
A72: 8- | B72: Trucks deck paint | C72: 5 | D72: New | E72: Local | F72: 50000 | G72: 31000 | H72: 66550 | I72: =SUM(L72:XEZ72) -> 0 | J72: =H72-I72 -> 66550
A73: 9- | B73: Batteries of Electric Stackers, Fork lifts and Trucks | C73: 11 | D73: New | E73: Local | F73: =1500000/2 -> 750000 | G73: 754583 | H73: 1000000 | I73: =SUM(L73:XEZ73) -> 0 | J73: =H73-I73 -> 1000000
A74: 10- | B74: Diesal Dispenser | C74: 2 | D74: New | E74: Local | F74: 50000 | G74: 39550 | H74: 100000 | I74: =SUM(L74:XEZ74) -> 0 | J74: =H74-I74 -> 100000
A75: 11- | B75: Longer Forks/Fork Sleeves for Forklift of Length 1670mm Sets | H75: 1000000 | I75: =SUM(L75:XEZ75) -> 0 | J75: =H75-I75 -> 1000000
I76: =SUM(L76:XEZ76) -> 0
A77: Sub Total (D): | F77: =SUM(F65:F76) -> 2420000 | G77: =SUM(G65:G76) -> 4111146.6 | H77: =SUM(H65:H76) -> 7675329.7 | I77: =SUM(I65:I76) -> 0 | J77: =SUM(J65:J76) -> 7675329.7
A78: E | B78: General Maintenance & Items
A79: 1- | B79: Mechanical/Utility Maintenance | C79: 1 | D79: New | E79: Local | F79: 3506350 | G79: 3501914.4 | H79: 3500000 | I79: =SUM(L79:XEZ79) -> 0 | J79: =H79-I79 -> 3500000
A80: 2- | B80: Electrical Maintenance (MV/LV/Trafo & General Plant Maint) | C80: 1 | D80: New | E80: Local | F80: 2500000 | G80: 2498091 | H80: 2500000 | I80: =SUM(L80:XEZ80) -> 0 | J80: =H80-I80 -> 2500000
A81: 3 | B81: Stamping Line | C81: 6 | D81: New | E81: Local | G81: 0 | H81: 1500000 | I81: =SUM(L81:XEZ81) -> 0 | J81: =H81-I81 -> 1500000
A82: 4 | B82: Catalytic Convertor | C82: 12 | D82: New | E82: Local | G82: 0 | H82: 1500000 | I82: =SUM(L82:XEZ82) -> 0 | J82: =H82-I82 -> 1500000
A83: 5 | B83: Die Development Center | C83: 7 | D83: New | E83: Local | G83: 0 | H83: 1000000 | I83: =SUM(L83:XEZ83) -> 0 | J83: =H83-I83 -> 1000000
A84: 3- | B84: Weld Shop (PSW & SSW) | C84: 1 | D84: New | E84: Local | F84: 950000 | G84: 289880 | H84: 400000 | I84: =SUM(L84:XEZ84) -> 0 | J84: =H84-I84 -> 400000
A85: 4- | B85: Weld Shop (PSW & SSW) Production Maint Items | C85: 1 | D85: New | E85: Local | F85: 347132 | G85: 797884.5 | H85: 789287 | I85: =SUM(L85:XEZ85) -> 0 | J85: =H85-I85 -> 789287
A86: 5- | B86: Pumps Repairing | C86: 1 | D86: New | E86: Local | F86: 150000 | G86: 0 | H86: 150000 | I86: =SUM(L86:XEZ86) -> 0 | J86: =H86-I86 -> 150000
A87: 6- | B87: Motor Re-Winding/Repairing | C87: 1 | D87: New | E87: Local | F87: 150000 | G87: 130200 | H87: 150000 | I87: =SUM(L87:XEZ87) -> 0 | J87: =H87-I87 -> 150000
A88: 7- | B88: Electronic Card Repairing | C88: All | D88: New | E88: Local | F88: 250000 | G88: 174800 | H88: 250000 | I88: =SUM(L88:XEZ88) -> 0 | J88: =H88-I88 -> 250000
A89: 8 | B89: General PEB Maintenance | C89: 1 | D89: New | E89: Local | F89: 500000 | G89: 68499 | H89: 1000000 | I89: =SUM(L89:XEZ89) -> 0 | J89: =H89-I89 -> 1000000
A90: 9 | B90: Epoxy Paint for whole plant | C90: 1 | D90: New | E90: Local | F90: 3000000 | G90: 1454000 | H90: 1000000 | I90: =SUM(L90:XEZ90) -> 0 | J90: =H90-I90 -> 1000000
A91: 10 | B91: Bracket Fan | C91: 5 | D91: New | E91: Local | F91: =78450*C91 -> 392250 | G91: 297500 | H91: =60000 -> 60000 | I91: =SUM(L91:XEZ91) -> 0 | J91: =H91-I91 -> 60000
A92: 11 | B92: Industrial Fans for RM , SFG Area & Weld | C92: 2 | D92: New | E92: Local | F92: =100000*C92 -> 200000 | G92: =SUM(I92:WUT92) -> 569115 | H92: =300000+269115 -> 569115 | I92: =SUM(L92:XEZ92) -> 0 | J92: =H92-I92 -> 569115
A93: 12 | B93: Corolla jigs repairing 6 jig ( clamp change ) (Production) | H93: 500000 | I93: =SUM(L93:XEZ93) -> 0 | J93: =H93-I93 -> 500000
A94: 13 | B94: Productivity improvement by jig addition/replacement/others | H94: 800000 | I94: =SUM(L94:XEZ94) -> 0 | J94: =H94-I94 -> 800000
A95: 14 | B95: PTC CREO | G95: 6543350
A96: Sub Total (E): | F96: =SUM(F79:F91) -> 11745732 | G96: =SUM(G79:G95) -> 16325234 | H96: =SUM(H79:H94) -> 15668402 | I96: =SUM(I79:I94) -> 0 | J96: =SUM(J79:J94) -> 15668402
A98: F | B98: Quality
A99: 1- | B99: SGS (ISO9001:2015) | C99: 1 | D99: New | E99: Local | F99: 114000 | G99: 92000 | H99: 224000 | I99: =SUM(L99:XEZ99) -> 0 | J99: =H99-I99 -> 224000
A100: 2- | B100: EMS 14001:2015 | C100: 1 | D100: New | E100: Local | F100: 114000 | G100: 111985 | H100: 112000 | I100: =SUM(L100:XEZ100) -> 0 | J100: =H100-I100 -> 112000
A101: 3- | B101: SEPA EMP Renewal (Yearly) | C101: 1 | D101: New | E101: Local | F101: 325000 | G101: 87000 | H101: 375000 | I101: =SUM(L101:XEZ101) -> 0 | J101: =H101-I101 -> 375000
A102: 4- | B102: Quarterly Environment monitoring + Waste disposal (x4) | C102: 4 | D102: New | E102: Local | F102: 300000 | G102: 139000 | H102: 336000 | I102: =SUM(L102:XEZ102) -> 0 | J102: =H102-I102 -> 336000
A103: 5- | B103: Faro Spare Parts | C103: 3 | D103: New | E103: Local | F103: 1134300 | G103: 638000 | H103: - | I103: =SUM(L103:XEZ103) -> 0
A104: 6- | B104: Instrument Calibration | C104: 1 | D104: New | E104: Local | F104: =120000+912000 -> 1032000 | G104: 980906 | H104: 120000 | I104: =SUM(L104:XEZ104) -> 0 | J104: =H104-I104 -> 120000
A105: 7- | B105: File Cabinet | C105: 1 | D105: New | E105: Local | F105: 100000 | G105: 0 | H105: 50000 | I105: =SUM(L105:XEZ105) -> 0 | J105: =H105-I105 -> 50000
A106: 8- | B106: QC Tool | C106: var | D106: New | E106: Local | F106: 400000 | G106: =350000-177562 -> 172438 | H106: 400000 | I106: =SUM(L106:XEZ106) -> 31900 | J106: =H106-I106 -> 368100 | N106: 31900
A107: 9- | B107: QCC and 5S slogan | C107: 3 | D107: New | E107: Local | F107: 200000 | G107: 0 | H107: 150000 | I107: =SUM(L107:XEZ107) -> 0 | J107: =H107-I107 -> 150000
...

Sheet Consuambles
A1: AGRIAUTO STAMPING COMPANY (PVT.) LTD.
A2: CONSUMABLES STORES
D4: BUDGET 2022-23 | K4: BUDGET 2023-24 | P4: BUDGET 2025-26 | X4: BUDGET 2026-27
A5: S.no | B5: Material Number | C5: Description | D5: Qty | E5: UOM | F5: Rate | G5: 20% Increase | H5: Increase Price | I5: Total | K5: Qty | L5: UOM | M5: Rate | N5: Total | P5: Qty | Q5: UOM | R5: Rate | S5: Total | U5: CONSUMPTION 1-1-2025 -- 1-1-2026 | V5: CONSUMPTION 1.1.2026 - 30.4.2026 | W5: QUARTER x 4 | X5: Qty | Y5: UOM | Z5: Rate | AA5: Total | AB5: UTILIZATION UPTO APR 26 | AC5: UTILIZATION UPTO JUN 26 | AD5: REASON | AF5: Budget Utilization | AG5: Remaining budget | AI5: 2000005366 | AJ5: 2000005365
A7: 1 | B7: PRC1-GEN-00003 | C7: Netted Gloves | D7: 60000 | E7: Sets | F7: 20 | G7: 4 | H7: 24 | I7: 1440000 | K7: 24000 | L7: Sets | M7: 20 | N7: 480000 | P7: 36000 | Q7: Sets | R7: 32 | S7: 1152000 | U7: 49104 | V7: 21984 | W7: 65952 | X7: 80000 | Y7: Sets | Z7: 30 | AA7: 2400000 | AB7: 1580011.6 | AC7: 1896013.9 | AD7: General reason : 79 man power increased from Last year with added C shift and upcoming new products in next year i.e. W&D and YXO | AF7: =SUM(AH7:XFD7) -> 0 | AG7: =AA7-AF7 -> 2400000
A8: 2 | B8: PRC1-GEN-00012 | C8: Kevlar Gloves | D8: 1200 | E8: Sets | F8: 480 | G8: 96 | H8: 576 | I8: 691200 | K8: 400 | L8: Sets | M8: 480 | N8: 192000 | P8: 600 | Q8: Sets | R8: 480 | S8: 288000 | U8: 647 | V8: 504 | W8: 1512 | X8: 1600 | Y8: Sets | Z8: 528 | AA8: 844800 | AB8: 486000 | AC8: 583200 | AF8: =SUM(AH8:XFD8) -> 0 | AG8: =AA8-AF8 -> 844800
A9: 3 | B9: PRC1-GEN-00001 | C9: Cotton Rags | D9: 3600 | E9: Kg | F9: 60 | G9: 12 | H9: 72 | I9: 259200 | K9: 1700 | L9: Kg | M9: 95 | N9: 161500 | P9: 2000 | Q9: Kg | R9: 95 | S9: 190000 | U9: 1997 | V9: 680 | W9: 2040 | X9: 2500 | Y9: KG | Z9: 95 | AA9: 237500 | AB9: 184300 | AC9: 221160 | AF9: =SUM(AH9:XFD9) -> 0 | AG9: =AA9-AF9 -> 237500
A10: 4 | B10: LUB-GEN-00003 | C10: Kerosene Oil | D10: 2400 | E10: Lts | F10: 210 | G10: 42 | H10: 252 | I10: 604800 | K10: 900 | L10: Ltr | M10: 325 | N10: 292500 | P10: 1200 | Q10: Ltr | R10: 320 | S10: 384000 | U10: 1309 | V10: 430 | W10: 1290 | X10: 1600 | Y10: Ltr | Z10: 320 | AA10: 512000 | AB10: 412550.19 | AC10: 495060.23 | AF10: =SUM(AH10:XFD10) -> 0 | AG10: =AA10-AF10 -> 512000
A11: 5 | B11: LUB-GEN-00018 | C11: SunRess Oil | D11: 600 | E11: Ltr | F11: 2570 | G11: 514 | H11: 3084 | I11: 1850400 | K11: 200 | L11: Ltr | M11: 6906 | N11: 1381200 | P11: 200 | Q11: Ltr | R11: 6906 | S11: 1381200 | U11: 357 | V11: 170 | W11: 510 | X11: 200 | Y11: Ltr | Z11: 6906 | AA11: 1381200 | AB11: 2176145.4 | AC11: 2611374.5 | AF11: =SUM(AH11:XFD11) -> 0 | AG11: =AA11-AF11 -> 1381200
A12: 6 | C12: JIER Line (Oil Replace) | X12: 4 | AA12: 4800000 | AF12: =SUM(AH12:XFD12) -> 0 | AG12: =AA12-AF12 -> 4800000
A13: 7 | C13: Cutting and Lubrication OIL for DDC | X13: 2 | AA13: 621425 | AF13: =SUM(AH13:XFD13) -> 0 | AG13: =AA13-AF13 -> 621425
A14: 8 | B14: CON-OLB-0007 | C14: Anticore 40 | D14: 1600 | E14: Ltr | F14: 350 | G14: 70 | H14: 420 | I14: 672000 | K14: 1800 | L14: Ltr | M14: 570 | N14: 1026000 | P14: 2000 | Q14: Ltr | R14: 598 | S14: 1196000 | U14: 2780 | V14: 780 | W14: 2340 | X14: 2800 | Y14: Ltr | Z14: 885 | AA14: 2478000 | AB14: 1451320 | AC14: 1741584 | AF14: =SUM(AH14:XFD14) -> 0 | AG14: =AA14-AF14 -> 2478000
A15: 9 | B15: HRD-WRE-00014 | C15: Cutting Disc 4" 1mm Rodius | D15: 1000 | E15: Nos | F15: 137 | G15: 27.4 | H15: 164.4 | I15: 164400 | K15: 300 | L15: Ea | M15: 200 | N15: 60000 | P15: 1500 | Q15: Ea | R15: 210 | S15: 315000 | U15: 712 | V15: 266 | W15: 798 | X15: 1000 | Y15: Ea | Z15: 210 | AA15: 210000 | AB15: 116785.86 | AC15: 140143.03 | AF15: =SUM(AH15:XFD15) -> 0 | AG15: =AA15-AF15 -> 210000
A16: 10 | B16: PRC1-GEN-00134 | C16: Argon Gas (Cylinder) | D16: 480 | E16: ea | F16: 3000 | G16: 600 | H16: 3600 | I16: 1728000 | K16: 200 | L16: Ea | M16: 4000 | N16: 800000 | P16: 150 | Q16: Ea | R16: 4000 | S16: 600000 | U16: 208 | V16: 84 | W16: 252 | X16: 230 | Y16: Ea | Z16: 4000 | AA16: 920000 | AB16: 760000 | AC16: 912000 | AF16: =SUM(AH16:XFD16) -> 0 | AG16: =AA16-AF16 -> 920000
A17: 11 | B17: MECH-ITM-00024 | C17: Arm Sleeves | D17: 2000 | E17: Sets | F17: 180 | G17: 36 | H17: 216 | I17: 432000 | K17: 200 | L17: Sets | M17: 180 | N17: 36000 | P17: 400 | Q17: Sets | R17: 200 | S17: 80000 | U17: 538 | V17: 283 | W17: 849 | X17: 1000 | Y17: Sets | Z17: 225 | AA17: 225000 | AB17: 126543.86 | AC17: 151852.63 | AF17: =SUM(AH17:XFD17) -> 0 | AG17: =AA17-AF17 -> 225000
A18: 12 | B18: PRC1-GEN-000012 | C18: Wrist Supporter | D18: 1600 | E18: Sets | F18: 170 | G18: 34 | H18: 204 | I18: 326400 | K18: 200 | L18: Sets | M18: 170 | N18: 34000 | P18: 350 | Q18: Sets | R18: 170 | S18: 59500 | U18: 389 | V18: 165 | W18: 495 | X18: 620 | Y18: Sets | Z18: 170 | AA18: 105400 | AB18: 69530 | AC18: 83436 | AF18: =SUM(AH18:XFD18) -> 0 | AG18: =AA18-AF18 -> 105400
A19: 13 | B19: PRC1-GEN-00007 | C19: Apron | D19: 1600 | E19: Nos | F19: 240 | G19: 48 | H19: 288 | I19: 460800 | K19: 100 | L19: Nos | M19: 315 | N19: 31500 | P19: 420 | Q19: Nos | R19: 210 | S19: 88200 | U19: 641 | V19: 249 | W19: 747 | X19: 850 | Y19: Nos | Z19: 210 | AA19: 178500 | AB19: 123480 | AC19: 148176 | AF19: =SUM(AH19:XFD19) -> 0 | AG19: =AA19-AF19 -> 178500
A20: 14 | B20: MECH-ITM-00020 | C20: Face shield welding | D20: 600 | E20: Nos | F20: 410 | G20: 82 | H20: 492 | I20: 295200 | K20: 150 | L20: Nos | M20: 300 | N20: 45000 | P20: 200 | Q20: Nos | R20: 350 | S20: 70000 | U20: 410 | V20: 185 | W20: 555 | X20: 680 | Y20: Nos | Z20: 600 | AA20: 408000 | AB20: 169900 | AC20: 203880 | AF20: =SUM(AH20:XFD20) -> 0 | AG20: =AA20-AF20 -> 408000
A21: 15 | B21: PRC1-GEN-00133 | C21: Ear Plugs | D21: 3600 | E21: Nos. | F21: 30 | G21: 6 | H21: 36 | I21: 129600 | K21: 150 | L21: Nos | M21: 35 | N21: 5250 | P21: 300 | Q21: Nos | R21: 23 | S21: 6900 | U21: 301 | V21: 121 | W21: 363 | X21: 450 | Y21: Nos | Z21: 23 | AA21: 10350 | AB21: 6785 | AC21: 8142 | AF21: =SUM(AH21:XFD21) -> 0 | AG21: =AA21-AF21 -> 10350
A22: 16 | B22: PRC1-GEN-00004 | C22: Dust Mask | D22: 20000 | E22: Nos | F22: 2.2 | G22: 0.44 | H22: 2.64 | I22: 52800 | N22: 0 | P22: 800 | Q22: Nos | R22: 1.25 | S22: 1000 | U22: 1129 | V22: 732 | W22: 2196 | X22: 3000 | Y22: Nos | Z22: 3 | AA22: 9000 | AB22: 1967.38 | AC22: 2360.856 | AF22: =SUM(AH22:XFD22) -> 0 | AG22: =AA22-AF22 -> 9000
A23: 17 | B23: MECH-ITM-00076 | C23: Safety Goggle | D23: 900 | E23: Nos. | F23: 200 | G23: 40 | H23: 240 | I23: 216000 | K23: 250 | L23: Nos | M23: 200 | N23: 50000 | P23: 300 | Q23: Nos | R23: 325 | S23: 97500 | U23: 377 | V23: 161 | W23: 483 | X23: 550 | Y23: Nos | Z23: 325 | AA23: 178750 | AB23: 113100 | AC23: 135720 | AD23: 278 CURRENT MAN POWER & 312 MAN POWER | AF23: =SUM(AH23:XFD23) -> 0 | AG23: =AA23-AF23 -> 178750
A24: 18 | B24: ERSA-SPARE-001568 | C24: Bump Caps | D24: 120 | E24: Nos | F24: 410 | G24: 82 | H24: 492 | I24: 59040 | K24: 20 | L24: Nos | M24: 450 | N24: 9000 | P24: 50 | Q24: Nos | R24: 1230 | S24: 61500 | U24: 41 | V24: 4 | W24: 12 | X24: 100 | Y24: Nos | Z24: 1210 | AA24: 121000 | AB24: 15976.45 | AC24: 19171.74 | AD24: -34 | AF24: =SUM(AH24:XFD24) -> 0 | AG24: =AA24-AF24 -> 121000
A25: 19 | B25: ERSA-SPARE-001499 | C25: Cutter Baldes | D25: 50 | E25: Sets | F25: 8882 | G25: 1776.4 | H25: 10658.4 | I25: 532920 | N25: 0 | P25: 50 | Q25: Nos | R25: 7500 | S25: 375000 | U25: 80 | V25: 24 | W25: 72 | X25: 100 | Y25: Nos | Z25: 7500 | AA25: 750000 | AB25: 532880.02 | AC25: 639456.02 | AF25: =SUM(AH25:XFD25) -> 0 | AG25: =AA25-AF25 -> 750000
A26: 20 | B26: ERSA-SPARE-001498 | C26: Weld Tip YT-16-D3-C | D26: 2000 | E26: Nos | F26: 225 | G26: 45 | H26: 270 | I26: 540000 | K26: 1000 | L26: Nos | M26: 280 | N26: 280000 | P26: 3000 | Q26: Nos | R26: 380 | S26: 1140000 | U26: 3770 | V26: 1500 | W26: 4500 | X26: 5000 | Y26: Nos | Z26: 385 | AA26: 1925000 | AB26: 1385500 | AC26: 1662600 | AF26: =SUM(AH26:XFD26) -> 0 | AG26: =AA26-AF26 -> 1925000
A27: 21 | B27: MECH-ITM-00632 | C27: Weld Tip W-CTR-13X6A | D27: 0 | E27: Nos | F27: 176 | G27: 35.2 | H27: 211.2 | I27: 0 | N27: 0 | P27: 1000 | Q27: Nos | R27: 335 | S27: 335000 | U27: 500 | V27: 200 | W27: 600 | X27: 700 | Y27: Nos | Z27: 355 | AA27: 248500 | AB27: 134552.96 | AC27: 161463.55 | AF27: =SUM(AH27:XFD27) -> 0 | AG27: =AA27-AF27 -> 248500
A28: 22 | B28: CON-GAS-0008 | C28: CO2 Cylinders for Gas Welding | D28: 100 | E28: Nos | F28: 1760 | G28: 352 | H28: 2112 | I28: 211200 | K28: 20 | L28: Nos | M28: 1760 | N28: 35200 | P28: 60 | Q28: Nos | R28: 1760 | S28: 105600 | U28: 95 | V28: 54 | W28: 162 | X28: 200 | Y28: Nos | Z28: 1760 | AA28: 352000 | AB28: 202400 | AC28: 242880 | AF28: =SUM(AH28:XFD28) -> 0 | AG28: =AA28-AF28 -> 352000
A29: 23 | B29: NSM-GEN-00093 | C29: Grease | D29: 180 | E29: Kg | F29: 360 | G29: 72 | H29: 432 | I29: 77760 | K29: 60 | L29: Kg | M29: 496 | N29: 29760 | P29: 64 | Q29: Kg | R29: 1325 | S29: 84800 | U29: 80 | V29: 7 | W29: 21 | X29: 80 | Y29: Kg | Z29: 1425 | AA29: 114000 | AB29: 91300 | AC29: 109560 | AF29: =SUM(AH29:XFD29) -> 0 | AG29: =AA29-AF29 -> 114000
A30: 24 | B30: PRC1-GEN-00418 | C30: LPG Gas Cylinders for Canteen | D30: 100 | E30: Ea | F30: 2200 | G30: 440 | H30: 2640 | I30: 264000 | K30: 90 | L30: Nos | M30: 3000 | N30: 270000 | P30: 60 | Q30: Nos | R30: 2500 | S30: 150000 | U30: 38 | V30: 15 | W30: 45 | X30: 50 | Y30: Nos | Z30: 2500 | AA30: 125000 | AB30: 85000 | AC30: 102000 | AF30: =SUM(AH30:XFD30) -> 0 | AG30: =AA30-AF30 -> 125000
A31: 25 | B31: ERSA-SPARE-001592 | C31: Brazing Rods | D31: 15 | E31: Packets | F31: 24300 | G31: 4860 | H31: 29160 | I31: 437400 | N31: 0 | P31: 50 | Q31: Nos | R31: 3000 | S31: 150000 | U31: 82 | V31: 37 | W31: 111 | X31: 100 | Y31: Nos | Z31: 6000 | AA31: 600000 | AB31: 346500 | AC31: 415800 | AF31: =SUM(AH31:XFD31) -> 0 | AG31: =AA31-AF31 -> 600000
A32: 26 | B32: XYZ | C32: Paint (Grey / White / Green / Black / Yellow / Red) | D32: 100 | E32: Tin | F32: 2200 | G32: 440 | H32: 2640 | I32: 264000 | K32: 72 | L32: Tin | M32: 3650 | N32: 262800 | P32: 100 | Q32: Tin | R32: 3850 | S32: 385000 | W32: 100 | X32: 100 | Y32: Tin | Z32: 3900 | AA32: 390000 | AB32: 161150.72 | AC32: 193380.86 | AF32: =SUM(AH32:XFD32) -> 0 | AG32: =AA32-AF32 -> 390000
A33: 27 | B33: MECH-ITM-00012 | C33: Cutting Discs 14" Rodius | D33: 70 | E33: Nos | F33: 640 | G33: 128 | H33: 768 | I33: 53760 | K33: 20 | L33: Nos | M33: 800 | N33: 16000 | P33: 100 | Q33: Nos | R33: 840 | S33: 84000 | U33: 15 | V33: 15 | W33: 45 | X33: 50 | Y33: Nos | Z33: 1425 | AA33: 71250 | AB33: 21000 | AC33: 25200 | AF33: =SUM(AH33:XFD33) -> 0 | AG33: =AA33-AF33 -> 71250
A34: 28 | B34: MECH-ITM-00013 | C34: Cutting Disc 7" Rodius | D34: 200 | E34: Nos | F34: 242 | G34: 48.4 | H34: 290.4 | I34: 58080 | N34: 0 | P34: 400 | Q34: Nos | R34: 375 | S34: 150000 | U34: 140 | V34: 25 | W34: 75 | X34: 200 | Y34: Nos | Z34: 375 | AA34: 75000 | AB34: 52500 | AC34: 63000 | AF34: =SUM(AH34:XFD34) -> 0 | AG34: =AA34-AF34 -> 75000
A35: 29 | B35: TOOL-GEN-00058 | C35: Grinding Disc 4" Rodius | D35: 450 | E35: Nos | F35: 175 | G35: 35 | H35: 210 | I35: 94500 | N35: 0 | P35: 600 | Q35: Nos | R35: 250 | S35: 150000 | U35: 133 | V35: 20 | W35: 60 | X35: 133 | Y35: Nos | Z35: 250 | AA35: 33250 | AB35: 10460.51 | AC35: 12552.612 | AF35: =SUM(AH35:XFD35) -> 0 | AG35: =AA35-AF35 -> 33250
A36: 30 | B36: HRD-WRE-00325 | C36: FLAP DISC 4" X 5/8" | D36: 1200 | E36: Nos | F36: 90 | G36: 18 | H36: 108 | I36: 129600 | K36: 150 | L36: Nos | M36: 90 | N36: 13500 | P36: 600 | Q36: Nos | R36: 88 | S36: 52800 | U36: 545 | V36: 200 | W36: 600 | X36: 650 | Y36: Nos | Z36: 90 | AA36: 58500 | AB36: 46618.12 | AC36: 55941.744 | AF36: =SUM(AH36:XFD36) -> 0 | AG36: =AA36-AF36 -> 58500
A37: 31 | B37: MECH-ITM-00886 | C37: Cutting Disc 5" Rodius | D37: 600 | E37: Nos | F37: 150 | G37: 30 | H37: 180 | I37: 108000 | K37: 100 | L37: Nos. | M37: 250 | N37: 25000 | P37: 500 | Q37: Nos | R37: 225 | S37: 112500 | U37: 327 | V37: 173 | W37: 519 | X37: 500 | Y37: Nos | Z37: 235 | AA37: 117500 | AB37: 68250 | AC37: 81900 | AF37: =SUM(AH37:XFD37) -> 0 | AG37: =AA37-AF37 -> 117500
A38: 32 | B38: MECH-ITM-00001 | C38: Welding Rods 2.5mm Zodian | D38: 90 | E38: Packets | F38: 1100 | G38: 220 | H38: 1320 | I38: 118800 | K38: 30 | L38: Packets | M38: 2235 | N38: 67050 | P38: 120 | Q38: Packets | R38: 2280 | S38: 273600 | U38: 62 | V38: 25 | W38: 75 | X38: 120 | Y38: Packets | Z38: 2280 | AA38: 273600 | AB38: 146220 | AC38: 175464 | AF38: =SUM(AH38:XFD38) -> 0 | AG38: =AA38-AF38 -> 273600
A39: 33 | B39: HRD-WRE-00015 | C39: Welding Rods 3.2mm Zodian | D39: 60 | E39: Packets | F39: 1700 | G39: 340 | H39: 2040 | I39: 122400 | K39: 40 | L39: Packets | M39: 3475 | N39: 139000 | P39: 70 | Q39: Packets | R39: 3773.75 | S39: 264162.5 | U39: 19 | V39: 8 | W39: 24 | X39: 40 | Y39: Packets | Z39: 3773.75 | AA39: 150950 | AB39: 75178.91 | AC39: 90214.692 | AF39: =SUM(AH39:XFD39) -> 0 | AG39: =AA39-AF39 -> 150950
A40: 34 | B40: HRD-WRE-00324 | C40: Cup Wire brush | D40: 1000 | E40: No. | F40: 120 | G40: 24 | H40: 144 | I40: 144000 | K40: 500 | L40: No. | M40: 145 | N40: 72500 | P40: 600 | Q40: Nos | R40: 280 | S40: 168000 | U40: 199 | V40: 79 | W40: 237 | X40: 250 | Y40: Nos | Z40: 280 | AA40: 70000 | AB40: 55160 | AC40: 66192 | AF40: =SUM(AH40:XFD40) -> 0 | AG40: =AA40-AF40 -> 70000
A41: 35 | B41: ERSA-SPARE-001750 | C41: REVOLVING WHEEL 6" | D41: 60 | E41: No. | F41: 1000 | G41: 200 | H41: 1200 | I41: 72000 | K41: 20 | L41: No. | M41: 1400 | N41: 28000 | P41: 150 | Q41: Nos | R41: 1050 | S41: 157500 | U41: 300 | V41: #N/A | W41: #N/A | X41: 400 | Y41: Nos | Z41: 1150 | AA41: 460000 | AB41: 278250 | AC41: 333900 | AF41: =SUM(AH41:XFD41) -> 0 | AG41: =AA41-AF41 -> 460000
A42: 36 | B42: ERSA-SPARE-000267 | C42: FIX WHEEL 6" | D42: 60 | E42: No. | F42: 880 | G42: 176 | H42: 1056 | I42: 63360 | K42: 20 | L42: No. | M42: 1200 | N42: 24000 | P42: 30 | Q42: Nos | R42: 1020 | S42: 30600 | U42: 84 | V42: #N/A | W42: #N/A | X42: 120 | Y42: Nos | Z42: 1050 | AA42: 126000 | AB42: 85369.57 | AC42: 102443.48 | AF42: =SUM(AH42:XFD42) -> 0 | AG42: =AA42-AF42 -> 126000
A43: 37 | B43: MECH-ITM-00719 | C43: CO2 wire 0.9mm | D43: 24 | E43: No. | F43: 7875 | G43: 1575 | H43: 9450 | I43: 226800 | K43: 10 | L43: No. | M43: 9000 | N43: 90000 | P43: 15 | Q43: Nos | R43: 8700 | S43: 130500 | U43: 16 | V43: #N/A | W43: #N/A | X43: 25 | Y43: Nos | Z43: 8700 | AA43: 217500 | AB43: 139200 | AC43: 167040 | AF43: =SUM(AH43:XFD43) -> 0 | AG43: =AA43-AF43 -> 217500
A44: 38 | B44: MECH-ITM-01112 | C44: CO2 wire 1.0mm | D44: 24 | E44: No. | F44: 7875 | G44: 1575 | H44: 9450 | I44: 226800 | K44: 10 | L44: No. | M44: 9000 | N44: 90000 | P44: 20 | Q44: Nos | R44: 8250 | S44: 165000 | U44: 27 | V44: 16 | W44: 48 | X44: 45 | Y44: Nos | Z44: 8250 | AA44: 371250 | AB44: 288750 | AC44: 346500 | AF44: =SUM(AH44:XFD44) -> 0 | AG44: =AA44-AF44 -> 371250
A45: 39 | B45: PRC1-GEN-00493 | C45: Castor Oil | K45: 300 | L45: Ltr | M45: 1500 | N45: 450000 | P45: 250 | Q45: Ltr | R45: 1050 | S45: 262500 | U45: 280 | V45: 80 | W45: 240 | X45: 350 | Y45: Ltr | Z45: 1050 | AA45: 367500 | AB45: 252000 | AC45: 302400 | AF45: =SUM(AH45:XFD45) -> 0 | AG45: =AA45-AF45 -> 367500
A46: 40 | B46: PRC1-GEN-00293 | C46: Paint Marker | K46: 100 | L46: Ea | M46: 150 | N46: 15000 | P46: 120 | Q46: Ea | R46: 180 | S46: 21600 | U46: 61 | V46: 17 | W46: 51 | X46: 120 | Y46: Ea | Z46: 180 | AA46: 21600 | AB46: 11171.43 | AC46: 13405.716 | AF46: =SUM(AH46:XFD46) -> 0 | AG46: =AA46-AF46 -> 21600
A47: 41 | B47: PRC1-GEN-00278 | C47: Cotton Tape (CLOTH TAPE 2") | E47: ea. | F47: 800 | G47: 160 | H47: 960 | I47: 0 | L47: ea. | N47: 0 | P47: 50 | Q47: Ea | R47: 1890 | S47: 94500 | U47: 70 | V47: 38 | W47: 114 | X47: 130 | Y47: Ea | Z47: 650 | AA47: 84500 | AB47: 59800 | AC47: 71760 | AF47: =SUM(AH47:XFD47) -> 0 | AG47: =AA47-AF47 -> 84500
A48: 42 | B48: ELEC-ITM-00266 | C48: Elfi | D48: 300 | E48: ea | F48: 30 | G48: 6 | H48: 36 | I48: 10800 | K48: 40 | L48: ea | M48: 250 | N48: 10000 | P48: 60 | Q48: Ea | R48: 100 | S48: 6000 | U48: 33 | V48: 11 | W48: 33 | X48: 60 | Y48: Ea | Z48: 110 | AA48: 6600 | AB48: 2750 | AC48: 3300 | AF48: =SUM(AH48:XFD48) -> 0 | AG48: =AA48-AF48 -> 6600
A49: 43 | B49: MECH-ITM-00036 | C49: Thinner | D49: 500 | E49: Ltr | F49: 280 | G49: 56 | H49: 336 | I49: 168000 | K49: 40 | L49: Ltr | M49: 350 | N49: 14000 | P49: 60 | Q49: Ltr | R49: 340 | S49: 20400 | U49: 100 | V49: 26 | W49: 78 | X49: 150 | Y49: Ltr | Z49: 430 | AA49: 64500 | AB49: 37663.6 | AC49: 45196.32 | AF49: =SUM(AH49:XFD49) -> 0 | AG49: =AA49-AF49 -> 64500
A50: 44 | B50: HRD-WRE-00370 | C50: BUFFING WHEEL SIZE 60/30 | S50: 0 | U50: 84 | V50: 101 | W50: 303 | X50: 370 | Y50: EA | Z50: 1250 | AA50: 462500 | AB50: 212650 | AC50: 255180 | AF50: =SUM(AH50:XFD50) -> 0 | AG50: =AA50-AF50 -> 462500
A51: 45 | B51: PRC1-GEN-00303 | C51: WELDING HELMET | P51: 50 | Q51: EA | R51: 410 | S51: 20500 | U51: 70 | V51: 41 | W51: 123 | X51: 150 | Y51: EA | Z51: 510 | AA51: 76500 | AB51: 45505.55 | AC51: 54606.66 | AF51: =SUM(AH51:XFD51) -> 0 | AG51: =AA51-AF51 -> 76500
A52: 46 | B52: PRC1-GEN-00324 | C52: A2 RING FOR SAFETY HELMET | P52: 50 | Q52: EA | R52: 230 | S52: 11500 | U52: 51 | V52: 42 | W52: 126 | X52: 160 | Y52: EA | Z52: 265 | AA52: 42400 | AB52: 16152.64 | AC52: 19383.168 | AF52: =SUM(AH52:XFD52) -> 0 | AG52: =AA52-AF52 -> 42400
A53: 47 | B53: PRC1-GEN-00325 | C53: SAFETY HELMET FITTING | P53: 150 | Q53: EA | R53: 180 | S53: 27000 | U53: 188 | V53: 51 | W53: 153 | X53: 250 | Y53: EA | Z53: 180 | AA53: 45000 | AB53: 31197.65 | AC53: 37437.18 | AF53: =SUM(AH53:XFD53) -> 0 | AG53: =AA53-AF53 -> 45000
A54: 48 | B54: PRC1-GEN-00151 | C54: Reflector Jacket | P54: 30 | Q54: EA | R54: 170 | S54: 5100 | U54: 72 | V54: 29 | W54: 87 | X54: 80 | Y54: EA | Z54: 475 | AA54: 38000 | AB54: 29975 | AC54: 35970 | AF54: =SUM(AH54:XFD54) -> 0 | AG54: =AA54-AF54 -> 38000
A55: 49 | B55: ERSA-SPARE-001528 | C55: Water Filter | P55: 50 | Q55: EA | R55: 542 | S55: 27100 | U55: 3 | V55: 2 | W55: 6 | X55: 30 | Y55: EA | Z55: 542 | AA55: 16260 | AB55: 2714.5 | AC55: 3257.4 | AF55: =SUM(AH55:XFD55) -> 0 | AG55: =AA55-AF55 -> 16260
A56: 50 | B56: HRD-WRE-00047 | C56: Orbital Sanding Paper 5" P#600 Mirka Fi | P56: 1500 | Q56: EA | R56: 125 | S56: 187500 | U56: 1760 | V56: 603 | W56: 1809 | X56: 2400 | Y56: EA | Z56: 125 | AA56: 300000 | AB56: 211125 | AC56: 253350 | AF56: =SUM(AH56:XFD56) -> 0 | AG56: =AA56-AF56 -> 300000
A57: 51 | B57: PRC1-GEN-00500 | C57: Grinding Disc 2" A36P Resibon | P57: 300 | Q57: EA | R57: 320 | S57: 96000 | U57: 254 | V57: 45 | W57: 135 | X57: 300 | Y57: EA | Z57: 320 | AA57: 96000 | AB57: 51200 | AC57: 61440 | AF57: =SUM(AH57:XFD57) -> 0 | AG57: =AA57-AF57 -> 96000
A58: 52 | B58: HRD-WRE-00024 | C58: LEATHER GLOVE | P58: 50 | Q58: EA | R58: 350 | S58: 17500 | U58: 47 | V58: 7 | W58: 21 | X58: 50 | Y58: EA | Z58: 355 | AA58: 17750 | AB58: 6744.11 | AC58: 8092.932 | AF58: =SUM(AH58:XFD58) -> 0 | AG58: =AA58-AF58 -> 17750
A59: 53 | B59: MECH-ITM-00015 | C59: WELDING GLASS TRANSPARENT | P59: 200 | Q59: EA | R59: 5 | S59: 1000 | U59: 122 | V59: 10 | W59: 30 | X59: 150 | Y59: EA | Z59: 5 | AA59: 750 | AB59: 294 | AC59: 352.8 | AF59: =SUM(AH59:XFD59) -> 0 | AG59: =AA59-AF59 -> 750
A60: 54 | B60: MECH-ITM-00016 | C60: WELDING GLASS BLACK | P60: 100 | Q60: EA | R60: 12 | S60: 1200 | U60: 30 | V60: 3 | W60: 9 | X60: 75 | Y60: EA | Z60: 12 | AA60: 900 | AB60: 324 | AC60: 388.8 | AF60: =SUM(AH60:XFD60) -> 0 | AG60: =AA60-AF60 -> 900
A61: 55 | B61: PRC1-GEN-00461 | C61: SPRAY BOTTLE PUMP | P61: 150 | Q61: EA | R61: 40 | S61: 6000 | U61: 126 | V61: 16 | W61: 48 | X61: 150 | Y61: EA | Z61: 100 | AA61: 15000 | AB61: 3393.26 | AC61: 4071.912 | AF61: =SUM(AH61:XFD61) -> 0 | AG61: =AA61-AF61 -> 15000
A62: 56 | B62: CON-GLI-0403 | C62: SPRAY BOTTLE | P62: 100 | Q62: EA | R62: 115 | S62: 11500 | U62: 98 | V62: 27 | W62: 81 | X62: 100 | Y62: EA | Z62: 250 | AA62: 25000 | AB62: 9157.1 | AC62: 10988.52 | AF62: =SUM(AH62:XFD62) -> 0 | AG62: =AA62-AF62 -> 25000
... A66: 60 | B66: PRC1-GEN-00434 | C66: NITROGEN GAS CYLINDER | P66: 12 | Q66: EA | R66: 3000 | S66: 36000 | U66: 11 | V66: 7 | W66: 21 | X66: 24 | Y66: EA | Z66: 3000 | AA66: 72000 | AB66: 36000 | AC66: 43200 | AF66: =SUM(AH66:XFD66) -> 0 | AG66: =AA66-AF66 -> 72000
A67: 61 | B67: PRC1-GEN-00457 | C67: Tarpaulin Canvas Cloth 18 x 30 ft. | U67: 19 | V67: 10 | W67: 30 | X67: 40 | Y67: Ea | Z67: 9650 | AA67: 386000 | AB67: 182000 | AC67: 218400 | AF67: =SUM(AH67:XFD67) -> 0 | AG67: =AA67-AF67 -> 386000
A68: 62 | B68: MECH-ITM-01206 | C68: CARTRIDGE FILTER (PPF 30") | V68: #N/A | W68: #N/A | X68: 140 | Y68: Ea | Z68: 630 | AA68: 88200 | AB68: 0 | AC68: 0 | AF68: =SUM(AH68:XFD68) -> 0 | AG68: =AA68-AF68 -> 88200
A69: 63 | B69: MECH-ITM-01207 | C69: BAG FILTER (7x32) | V69: #N/A | W69: #N/A | X69: 14 | Y69: Ea | Z69: 1300 | AA69: 18200 | AB69: 0 | AC69: 0 | AF69: =SUM(AH69:XFD69) -> 0 | AG69: =AA69-AF69 -> 18200
A70: 64 | B70: MECH-ITM-01208 | C70: RO MINERALS BOTTLES | V70: #N/A | W70: #N/A | X70: 14 | Y70: Ea | Z70: 500 | AA70: 7000 | AB70: 0 | AC70: 0 | AF70: =SUM(AH70:XFD70) -> 0 | AG70: =AA70-AF70 -> 7000
A71: 65 | B71: PRC1-GEN-00549 | C71: RO CHEMICAL A110 | V71: 25 | W71: 75 | X71: 330 | Y71: Kg | Z71: 829 | AA71: 273570 | AB71: 20725 | AC71: 24870 | AF71: =SUM(AH71:XFD71) -> 0 | AG71: =AA71-AF71 -> 273570
A72: 66 | B72: PRC1-GEN-00550 | C72: RO CHEMICAL CB-600 | V72: #N/A | W72: #N/A | X72: 330 | Y72: Kg | Z72: 829 | AA72: 273570 | AB72: 0 | AC72: 0 | AF72: =SUM(AH72:XFD72) -> 0 | AG72: =AA72-AF72 -> 273570
A73: 67 | C73: Different Electrical consumables | D73: 1 | E73: ea | F73: 300000 | G73: 60000 | H73: 360000 | I73: 360000 | K73: 1 | L73: ea | M73: 500000 | N73: 500000 | P73: 1 | Q73: Ea | R73: 395735 | S73: 395735 | V73: #N/A | W73: #N/A | X73: 1 | Y73: Ea | Z73: 1334488 | AA73: 1334488 | AB73: 790364.56 | AC73: 948437.47 | AF73: =SUM(AH73:XFD73) -> 0 | AG73: =AA73-AF73 -> 1334488
A74: 68 | C74: Die Maintenance Consumables | I74: 1511840 | K74: 1 | L74: ea | M74: 1000000 | N74: 1000000 | P74: 1 | Q74: Ea | R74: 1700940 | S74: 1700940 | V74: #N/A | W74: #N/A | X74: 1 | Y74: Ea | Z74: 3419955.8 | AA74: 3419955.8 | AB74: 1216369.4 | AC74: 1459643.3 | AF74: =SUM(AH74:XFD74) -> 0 | AG74: =AA74-AF74 -> 3419955.8
A75: 69 | C75: Catalytic Converter Machine Consumables | K75: 1 | L75: ea | M75: 1323717 | N75: 1323717 | P75: 1 | Q75: Ea | R75: 988048 | S75: 988048 | V75: #N/A | W75: #N/A | X75: 1 | Y75: Ea | Z75: 342267.66 | AA75: 342267.66 | AB75: 45941.54 | AC75: 55129.848 | AF75: =SUM(AH75:XFD75) -> 0 | AG75: =AA75-AF75 -> 342267.66
A76: 70 | C76: Weld Consumable | K76: 1 | L76: ea | M76: 1262606 | N76: 1262606 | P76: 1 | Q76: Ea | R76: 0 | S76: 0 | V76: #N/A | W76: #N/A | X76: 1 | Y76: Ea | Z76: 650406.5 | AA76: 650406.5 | AB76: 322091 | AC76: 386509.2 | AF76: =SUM(AH76:XFD76) -> 95 | AG76: =AA76-AF76 -> 650311.5 | AJ76: 95
I77: 15177860 | AA77: =SUM(AA7:AA76) -> 30953763 | AB77: 15682866 | AC77: 18819439 | AF77: =SUM(AF7:AF76) -> 95 | AG77: =SUM(AG7:AG76) -> 30953668
A79: ADDITIONAL R&M
A81: 1 | B81: ERSA-SPARE-001287 | C81: Oil filter ( Fork Lifter ) | P81: 10 | Q81: EA | R81: 800 | S81: 8000 | U81: 7 | V81: 2 | W81: 6 | X81: 10 | Y81: EA | Z81: 800 | AA81: 8000 | AB81: 5600 | AC81: 6720 | AF81: =SUM(AH81:XFD81) -> 0 | AG81: =AA81-AF81 -> 8000
A82: 2 | B82: ERSA-SPARE-001288 | C82: Diesel filter ( Fork Lifter ) | P82: 10 | Q82: EA | R82: 1700 | S82: 17000 | U82: 7 | V82: 2 | W82: 6 | X82: 10 | Y82: EA | Z82: 1700 | AA82: 17000 | AB82: 11900 | AC82: 14280 | AF82: =SUM(AH82:XFD82) -> 0 | AG82: =AA82-AF82 -> 17000
A83: 3 | B83: ERSA-SPARE-001289 | C83: Air filter ( Fork Lifter ) | P83: 10 | Q83: EA | R83: 2500 | S83: 25000 | U83: 7 | V83: 2 | W83: 6 | X83: 10 | Y83: EA | Z83: 2500 | AA83: 25000 | AB83: 17500 | AC83: 21000 | AF83: =SUM(AH83:XFD83) -> 0 | AG83: =AA83-AF83 -> 25000
A84: 4 | B84: PRC1-GEN-00362 | C84: OIL FILTER OF 4TON LIFTER | P84: 5 | Q84: EA | R84: 2266 | S84: 11330 | U84: 3 | V84: 1 | W84: 3 | X84: 5 | Y84: EA | Z84: 3550 | AA84: 17750 | AB84: 8653.69 | AC84: 10384.428 | AF84: =SUM(AH84:XFD84) -> 0 | AG84: =AA84-AF84 -> 17750
A85: 5 | B85: PRC1-GEN-00363 | C85: DIESEL FILTER OF 4TON LIFTER | P85: 5 | Q85: EA | R85: 2270 | S85: 11350 | U85: 3 | V85: 1 | W85: 3 | X85: 5 | Y85: EA | Z85: 2600 | AA85: 13000 | AB85: 4932.59 | AC85: 5919.108 | AF85: =SUM(AH85:XFD85) -> 0 | AG85: =AA85-AF85 -> 13000
A86: 6 | B86: PRC1-GEN-00364 | C86: AIR FILTER OF 4TON LIFTER | P86: 5 | Q86: EA | R86: 3500 | S86: 17500 | U86: 3 | V86: #N/A | W86: #N/A | X86: 5 | Y86: EA | Z86: 6000 | AA86: 30000 | AB86: 8666.67 | AC86: 10400.004 | AF86: =SUM(AH86:XFD86) -> 0 | AG86: =AA86-AF86 -> 30000
A87: 7 | B87: ERSA-SPARE-001293 | C87: Distal water bottle ( Fork Lifter ) | P87: 200 | Q87: EA | R87: 100 | S87: 20000 | U87: 78 | V87: 69 | W87: 207 | X87: 225 | Y87: EA | Z87: 150 | AA87: 33750 | AB87: 15791.17 | AC87: 18949.404 | AF87: =SUM(AH87:XFD87) -> 0 | AG87: =AA87-AF87 -> 33750
A88: 8 | B88: PRC1-GEN-00276 | C88: BRAKE OIL SEKON | P88: 10 | Q88: EA | R88: 810 | S88: 8100 | U88: 2 | V88: 2 | W88: 6 | X88: 10 | Y88: EA | Z88: 810 | AA88: 8100 | AB88: 1620 | AC88: 1944 | AF88: =SUM(AH88:XFD88) -> 0 | AG88: =AA88-AF88 -> 8100
A89: 9 | B89: ERSA-SPARE-001292 | C89: Engine Oil Ultra Gold (Fork Lifter) | P89: 200 | Q89: EA | R89: 1150 | S89: 230000 | U89: 226 | V89: 100 | W89: 300 | X89: 350 | Y89: Ltr | Z89: 1050 | AA89: 367500 | AB89: 270000 | AC89: 324000 | AF89: =SUM(AH89:XFD89) -> 0 | AG89: =AA89-AF89 -> 367500
A90: 10 | C90: Lamination Machine | K90: 1 | L90: ea. | M90: 20000 | N90: 20000 | P90: 1 | Q90: Ea | R90: 20000 | S90: 20000 | V90: #N/A | W90: #N/A | X90: 1 | Y90: Ea | Z90: 20000 | AA90: 20000 | AF90: =SUM(AH90:XFD90) -> 9500 | AG90: =AA90-AF90 -> 10500 | AI90: 9500
AA91: =SUM(AA81:AA90) -> 540100 | AB91: 344664.12 | AC91: 413596.94 | AF91: =SUM(AF81:AF90) -> 9500 | AG91: =SUM(AG81:AG90) -> 530600
A92: CARTAGE
A94: 1 | B94: LUB-GEN-00001 | C94: Diesel for Fork Lift, Trucks & ASC Genset | D94: 40000 | E94: liter | F94: 209.556 | H94: 209.556 | I94: 8382240 | K94: 20000 | L94: liter | M94: 300 | N94: 6000000 | P94: 12000 | Q94: liter | R94: 318 | S94: 3816000 | U94: 25045 | V94: 9002 | W94: 27006 | X94: 26000 | Y94: liter | Z94: 340 | AA94: 8840000 | AB94: 6562459.7 | AC94: 7874951.6 | AD94: Increased Fuel prices which is leading to massively increase Cartrage Budget | AF94: =SUM(AH94:XFD94) -> 0 | AG94: =AA94-AF94 -> 8840000
A95: 2 | C95: RM Cartage from ASC to AIL | D95: 960 | E95: MT | F95: 666 | H95: 666 | I95: 639360 | K95: 12 | L95: ea | M95: 16666.667 | N95: 200000 | P95: 12 | Q95: EA | R95: 25000 | S95: 300000 | V95: #N/A | W95: #N/A | X95: 12 | Y95: EA | Z95: 156000 | AA95: 1872000 | AB95: 863975 | AC95: 1036770 | AF95: =SUM(AH95:XFD95) -> 0 | AG95: =AA95-AF95 -> 1872000
A96: 3 | C96: RM Cartage from ISL/MIDP to ASC | D96: 3600 | E96: MT | F96: 600 | H96: 600 | I96: 2160000 | K96: 12 | L96: MT | M96: 16666.667 | N96: 200000 | P96: 12 | Q96: EA | R96: 25000 | S96: 300000 | V96: #N/A | W96: #N/A | X96: 3 | Y96: EA | Z96: 1500000 | AA96: 4500000 | AB96: 2454251.8 | AC96: 2945102.1 | AF96: =SUM(AH96:XFD96) -> 0 | AG96: =AA96-AF96 -> 4500000
A97: 4 | C97: Transporation Fuel Tank | D97: 12 | E97: Trip | F97: 145000 | I97: 1740000 | K97: 12 | L97: Trip | M97: 200000 | N97: 2400000 | P97: 12 | Q97: EA | R97: 100000 | S97: 1200000 | V97: #N/A | W97: #N/A | X97: 26 | Y97: EA | Z97: 200000 | AA97: 5200000 | AB97: 3628000 | AC97: 4353600 | AF97: =SUM(AH97:XFD97) -> 0 | AG97: =AA97-AF97 -> 5200000
I98: 12921600 | N98: 8800000 | S98: 5616000 | AA98: =SUM(AA94:AA97) -> 20412000 | AB98: 13508686 | AC98: 16210424 | AF98: =SUM(AF94:AF97) -> 0 | AG98: =SUM(AG94:AG97) -> 20412000
A99: ADMINISTRATIVE COST
A101: 1 | B101: PRC1-GEN-00328 | C101: Uniform T-Shirt (02 ea) | D101: 1000 | E101: Ea | F101: 645 | G101: 129 | H101: 774 | I101: 774000 | K101: 500 | L101: Ea | M101: 1000 | N101: 500000 | P101: 1000 | Q101: Ea | R101: 840 | S101: 840000 | U101: 576 | V101: 91 | W101: 273 | X101: 750 | Y101: Ea | Z101: 840 | AA101: 630000 | AB101: 516600 | AC101: 619920 | AF101: =SUM(AH101:XFD101) -> 0 | AG101: =AA101-AF101 -> 630000
A102: 3 | B102: PRC1-GEN-00387 | C102: Safety Shoes | D102: 200 | E102: Pa | F102: 1825 | G102: 365 | H102: 2190 | I102: 438000 | K102: 40 | L102: Pa | M102: 2200 | N102: 88000 | P102: 300 | Q102: PA | R102: 2550 | S102: 765000 | U102: 252 | V102: 53 | W102: 159 | X102: 250 | Y102: PA | Z102: 2870 | AA102: 717500 | AB102: 655754.43 | AC102: 786905.32 | AF102: =SUM(AH102:XFD102) -> 0 | AG102: =AA102-AF102 -> 717500
A103: 4 | B103: PRC1-GEN-00114 | C103: Printing & Stationary | D103: 12 | E103: ea | F103: 65000 | G103: 13000 | H103: 78000 | I103: 936000 | K103: 12 | L103: ea | M103: 30000 | N103: 360000 | P103: 12 | Q103: Ea | R103: 20000 | S103: 240000 | V103: #N/A | W103: #N/A | X103: 12 | Y103: Ea | Z103: 20000 | AA103: 240000 | AF103: =SUM(AH103:XFD103) -> 0 | AG103: =AA103-AF103 -> 240000
A104: 5 | B104: XYZ | C104: Parmanent Marker for Welding & other departments | D104: 15000 | E104: ea | F104: 34 | G104: 6.8 | H104: 40.8 | I104: 612000 | K104: 5000 | L104: ea | M104: 49 | N104: 245000 | P104: 5000 | Q104: Ea | R104: 50 | S104: 250000 | U104: 7234 | V104: #N/A | W104: #N/A | X104: 8000 | Y104: Ea | Z104: 65 | AA104: 520000 | AB104: 369592.89 | AC104: 443511.47 | AF104: =SUM(AH104:XFD104) -> 0 | AG104: =AA104-AF104 -> 520000
A105: 6 | B105: PRC1-GEN-00486 | C105: Board Marker | P105: 700 | Q105: Ea | R105: 48 | S105: 33600 | U105: 1668 | V105: 782 | W105: 2346 | X105: 2400 | Y105: Ea | Z105: 65 | AA105: 156000 | AB105: 88400.11 | AC105: 106080.13 | AF105: =SUM(AH105:XFD105) -> 0 | AG105: =AA105-AF105 -> 156000
A106: 7 | B106: PRC1-GEN-00445 | C106: A4 Color Paper | D106: 600 | E106: ea | F106: 850 | G106: 170 | H106: 1020 | I106: 612000 | K106: 200 | L106: ea | M106: 1625 | N106: 325000 | P106: 120 | Q106: Ea | R106: 440 | S106: 52800 | U106: 205 | V106: 77 | W106: 231 | X106: 300 | Y106: Ea | Z106: 440 | AA106: 132000 | AB106: 85080.61 | AC106: 102096.73 | AF106: =SUM(AH106:XFD106) -> 20000 | AG106: =AA106-AF106 -> 112000 | AH106: 20000
A107: 8 | B107: PRC1-GEN-00481 | C107: Paper Rim A4 | P107: 400 | Q107: Ea | R107: 1720 | S107: 688000 | U107: 413 | V107: 134 | W107: 402 | X107: 430 | Y107: Ea | Z107: 1720 | AA107: 739600 | AB107: 407966.86 | AC107: 489560.23 | AF107: =SUM(AH107:XFD107) -> 0 | AG107: =AA107-AF107 -> 739600
A108: 9 | B108: PRC1-GEN-00487 | C108: Paper Rim A3 | P108: 20 | Q108: Ea | R108: 3376 | S108: 67520 | U108: 18 | V108: 5 | W108: 15 | X108: 25 | Y108: Ea | Z108: 2800 | AA108: 70000 | AB108: 30358.78 | AC108: 36430.536 | AF108: =SUM(AH108:XFD108) -> 0 | AG108: =AA108-AF108 -> 70000
A109: 10 | B109: PRC1-GEN-00208 | C109: LAMINATION SHEET A4 | P109: 1800 | Q109: Ea | R109: 18 | S109: 32400 | U109: 2199 | V109: 243 | W109: 729 | X109: 2200 | Y109: Ea | Z109: 18 | AA109: 39600 | AB109: 25920 | AC109: 31104 | AF109: =SUM(AH109:XFD109) -> 0 | AG109: =AA109-AF109 -> 39600
...

Sheet Sales Promotion Budget
B2: Sales Promotion Budget - 2026/27
C4: Exp. Rate | D4: Nos. | E4: Exp. Budget | G4: LY Actual
B6: Corporate Video: Edit to Add diversification Portion | C6: 250000 | D6: 1 | E6: 250000 | G6: 1800000 | H6: asc
B8: After Market Promotional Exp.
B9: Dealer Incentive | D9: 0.06 | E9: =K9*D9 -> 81000000 | G9: =1150000000*6% -> 69000000 | H9: ail | I9: =E9-G9 -> 12000000 | J9: Dealer Sale | K9: =K11-K10 -> 1350000000 | M9: =K11*0.06 -> 84000000
B10: Dealer/Mechanic Meet | C10: 1300000 | D10: 3 | E10: =D10*C10 -> 3900000 | G10: 2049119 | H10: asc | J10: Others | K10: 50000000
E11: =SUM(E9:E10) -> 84900000 | G11: =SUM(G9:G10) -> 71049119 | K11: 1400000000
B13: Advertising Agency - Retainership Fee | E13: 900000 | G13: 305268
B15: General Promotional Items Exp
B16: P-Cap | C16: 650 | D16: 1000 | E16: =D16*C16 -> 650000
B17: T-Shirt | C17: 2000 | D17: 1000 | E17: =D17*C17 -> 2000000
B18: Note Book | C18: 300 | D18: 1000 | E18: =D18*C18 -> 300000
B19: Miscellaneous (Broacher & Others) | E19: 300000
B20: Executive Giveaways | C20: 6500 | D20: 50 | E20: =D20*C20 -> 325000
E21: =SUM(E16:E20) -> 3575000 | G21: 927525 | H21: asc
B23: Shock Absorber - Export
B24: Exhibition Participation (Shocks/Brake Pads)- Jun'27 | C24: @ $5392 | D24: 1 | E24: =[52]istanbul!I26 -> 1586800 | H24: asc
B25: Petromin Samples (10 Types - 2 each) | E25: 206000 | H25: ail
E26: =SUM(E24:E25) -> 1792800
B27: Power Sector
B28: Enfrashare Sample | E28: 400000 | H28: ail
B29: Ed Boxes for ABAD 9@ 30k each ( Display) | E29: 270000 | H29: ail
B30: Power Sector - Educational order approval expenses. (LESCO) | E30: 2000000 | H30: asc
B31: FOC Educational Order Meter Boxes LESCO (5@40k) | E31: 800000 | H31: ail
E32: =SUM(E28:E31) -> 3470000 | G32: =153022+56000 -> 209022
B34: Waiting Chair
B35: Salesman Incentive | C35: 1000/Chair | D35: 2800 | H35: ail
B36: Exhibition Participation ( IAPEX LHR/KHI) | C36: 1500000 | D36: 1 | E36: =D36*C36 -> 1500000 | H36: asc
B37: Advertising ( Magazine Ads, BR/NW/Dawn) 2 inserts | E37: 1000000 | H37: asc
B38: Upholstery Color Selectors Shade Samples for Customers | C38: 100 | D38: 500 | E38: =D38*C38 -> 50000 | H38: ail
B39: Paid visits to Plant of Partners | E39: ='[52]Paid Visits'!L8 -> 668500 | H39: asc
B40: Social Media Paid Push | E40: 100000 | H40: asc
E41: =SUM(E35:E40) -> 3318500
B43: Misc. | G43: 1018510 | H43: MT Exp.
G44: 1274250 | H44: PAPs Exp.
B46: Grand Total | E46: =E41+E32+E26+E21+E13+E11+E6+E43 -> 98206300 | G46: =G41+G32+G26+G21+G13+G11+G6+G43+G44 -> 76583694 | H46: =G46-G9 -> 7583694
B48: Company wise Distribution
B49: AIL | E49: =E9 -> 81000000
B50: ASC | E50: =E46-E49 -> 17206300
E51: =E49+E50 -> 98206300
E56: CEO

Sheet Sheet2
A1: FY 2021-22 (Rs.) | C1: FY 2022-23 (Rs.) | E1: FY 2023-24 (Rs.) | G1: FY 2024-25 (Rs.) | I1: FY 2025-26 (Rs.) | K1: FY 2026-27 (Rs.) | WZC1: Budget Utilization | WZD1: Remaining budget | WZE1: Utilization %
A2: Budget | B2: Actual | C2: Budget | D2: Actual | E2: Budget | F2: Actual | G2: Budget | H2: Actual | I2: Budget | J2: Actual | K2: Budget | L2: Actual
A3: 53 | B3: 78.16 | C3: 110 | D3: 25.85 | E3: 59.5 | F3: 64.64 | G3: 105.5 | H3: 58.66 | I3: 98 | J3: 78.16 | K3: 92 | N3: 2021 | O3: 26185857
N4: 2022 | O4: 78162905
N5: 2023 | O5: 25858204
N6: 2024 | O6: 64640138
N7: 2025 | O7: 58663408
N8: 2026 | O8: 78168862
B10: 2021-22 | C10: Budget | D10: 53
C11: Actual | D11: 78.16
B12: 2022-23 | C12: Budget | D12: 110
C13: Actual | D13: 25.85
B14: 2023-24 | C14: Budget | D14: 59.5
C15: Actual | D15: 64.64
B16: 2024-25 | C16: Budget | D16: 105.5
C17: Actual | D17: 58.66
B18: 2025-26 | C18: Budget | D18: 98
C19: Actual | D19: 78.16
B20: 2026-27 | C20: Budget | D20: 92
C21: Actual
C32: 2021-22 | D32: 2022-23 | E32: 2023-24 | F32: 2024-25 | G32: 2025-26 | H32: 2026-27
B33: Budget | C33: 74.31 | D33: 67.19 | E33: 65.47 | F33: 104.5 | G33: 90.58 | H33: 116
B34: Actual | C34: 78.16 | D34: 25.86 | E34: 64.64 | F34: 58.66 | G34: 93.72
B35: IT | H35: 48
